ivy/__init__.py
ivy/debugger.py
ivy/framework_handler.py
ivy/verbosity.py
ivy/wrapper.py
ivy/compiler/__init__.py
ivy/compiler/compiler.py
ivy/compiler/globals.py
ivy/compiler/graph.py
ivy/compiler/helpers.py
ivy/compiler/op_logging.py
ivy/compiler/param.py
ivy/core/__init__.py
ivy/core/compilation.py
ivy/core/container.py
ivy/core/device.py
ivy/core/general.py
ivy/core/gradients.py
ivy/core/image.py
ivy/core/linalg.py
ivy/core/logic.py
ivy/core/math.py
ivy/core/meta.py
ivy/core/multi_node.py
ivy/core/nest.py
ivy/core/random.py
ivy/core/reductions.py
ivy/core/wrapped.py
ivy/core/array/__init__.py
ivy/core/array/array_device.py
ivy/core/array/array_general.py
ivy/core/array/array_gradients.py
ivy/core/array/array_image.py
ivy/core/array/array_linalg.py
ivy/core/array/array_logic.py
ivy/core/array/array_math.py
ivy/core/array/array_meta.py
ivy/core/array/array_random.py
ivy/core/array/array_reductions.py
ivy/jax/__init__.py
ivy/jax/core/__init__.py
ivy/jax/core/device.py
ivy/jax/core/general.py
ivy/jax/core/gradients.py
ivy/jax/core/image.py
ivy/jax/core/linalg.py
ivy/jax/core/logic.py
ivy/jax/core/math.py
ivy/jax/core/random.py
ivy/jax/core/reductions.py
ivy/jax/nn/__init__.py
ivy/jax/nn/activations.py
ivy/jax/nn/converters.py
ivy/jax/nn/layers.py
ivy/mxnet/__init__.py
ivy/mxnet/core/__init__.py
ivy/mxnet/core/device.py
ivy/mxnet/core/general.py
ivy/mxnet/core/gradients.py
ivy/mxnet/core/image.py
ivy/mxnet/core/linalg.py
ivy/mxnet/core/logic.py
ivy/mxnet/core/math.py
ivy/mxnet/core/random.py
ivy/mxnet/core/reductions.py
ivy/mxnet/nn/__init__.py
ivy/mxnet/nn/activations.py
ivy/mxnet/nn/layers.py
ivy/neural_net_functional/__init__.py
ivy/neural_net_functional/activations.py
ivy/neural_net_functional/layers.py
ivy/neural_net_functional/losses.py
ivy/neural_net_functional/norms.py
ivy/neural_net_stateful/__init__.py
ivy/neural_net_stateful/activations.py
ivy/neural_net_stateful/converters.py
ivy/neural_net_stateful/initializers.py
ivy/neural_net_stateful/layers.py
ivy_core-1.1.10.dist-info/LICENSE
ivy_core-1.1.10.dist-info/METADATA
ivy_core-1.1.10.dist-info/WHEEL
ivy_core-1.1.10.dist-info/top_level.txt
ivy_core-1.1.10.dist-info/RECORD
