Metadata-Version: 2.1
Name: ivy-core
Version: 1.1.10
Summary: The unified machine learning framework, enabling framework-agnostic functions, layers and libraries.
Home-page: https://ivy-dl.org/ivy
Author: Ivy Team
Author-email: ivydl.team@gmail.com
License: Apache 2.0
Project-URL: Docs, https://ivy-dl.org/ivy/
Project-URL: Source, https://github.com/ivy-dl/ivy
Classifier: License :: OSI Approved :: Apache Software License
License-File: LICENSE
